README.md
setup.py
petact/__init__.py
petact/petact.py
petact.egg-info/PKG-INFO
petact.egg-info/SOURCES.txt
petact.egg-info/dependency_links.txt
petact.egg-info/entry_points.txt
petact.egg-info/top_level.txt