Metadata-Version: 1.1
Name: petact
Version: 0.1.0
Summary: A package extraction tool
Home-page: https://github.com/matthewscholefield/petact
Author: Matthew Scholefield
Author-email: matthew331199@gmail.com
License: UNKNOWN
Keywords: tar extraction web download dependencies
Platform: UNKNOWN
Classifier: Development Status :: 3 - Alpha
Classifier: Intended Audience :: Developers
Classifier: License :: OSI Approved :: MIT License
Classifier: Topic :: System :: Filesystems
Classifier: Topic :: System :: Archiving :: Compression
Classifier: Topic :: Software Development :: Libraries :: Python Modules
Classifier: Programming Language :: Python :: 2
Classifier: Programming Language :: Python :: 2.7
Classifier: Programming Language :: Python :: 3
Classifier: Programming Language :: Python :: 3.4
Classifier: Programming Language :: Python :: 3.5
Classifier: Programming Language :: Python :: 3.6
